airflow_smartsheet/__init__.py
airflow_smartsheet/smartsheet_plugin.py
airflow_smartsheet/hooks/__init__.py
airflow_smartsheet/hooks/smartsheet_hook.py
airflow_smartsheet/operators/__init__.py
airflow_smartsheet/operators/enums.py
airflow_smartsheet/operators/smartsheet_operator.py
airflow_smartsheet_plugin-0.2.0.dist-info/LICENSE
airflow_smartsheet_plugin-0.2.0.dist-info/METADATA
airflow_smartsheet_plugin-0.2.0.dist-info/WHEEL
airflow_smartsheet_plugin-0.2.0.dist-info/entry_points.txt
airflow_smartsheet_plugin-0.2.0.dist-info/top_level.txt
airflow_smartsheet_plugin-0.2.0.dist-info/RECORD
