Metadata-Version: 2.1
Name: airflow-smartsheet-plugin
Version: 0.2.0
Summary: An Apache Airflow plugin to export Smartsheet sheets.
Home-page: https://github.com/xyx0826/Airflow-Smartsheet
Author: xyx0826
Author-email: xyx0826@hotmail.com
License: UNKNOWN
Platform: UNKNOWN
Classifier: Programming Language :: Python :: 3
Classifier: License :: OSI Approved :: MIT License
Classifier: Operating System :: POSIX :: Linux
Classifier: Environment :: Plugins
